emojiflag/__init__.py
emojiflag/emojiflag.py
emojiflag/utils.py
tests/__init__.py
tests/test_emojiflag.py
emojiflag-1.0.2.dist-info/LICENSE
emojiflag-1.0.2.dist-info/METADATA
emojiflag-1.0.2.dist-info/WHEEL
emojiflag-1.0.2.dist-info/top_level.txt
emojiflag-1.0.2.dist-info/RECORD
