Metadata-Version: 2.1
Name: emojiflag
Version: 1.0.2
Summary: Emoji country flags for language codes and LCID's
Home-page: https://github.com/lotrekagency/emojiflag
Author: Lotrek
Author-email: dimmitutto@lotrek.it
License: MIT
Platform: UNKNOWN
Classifier: Programming Language :: Python
Classifier: Programming Language :: Python :: 3
